CHANGES.txt
LICENSE.txt
MANIFEST.in
README.txt
bootstrap.py
buildout.cfg
setup.py
eggs/BTrees-6.1-py3.10-win-amd64.egg/EGG-INFO/LICENSE.txt
eggs/BTrees-6.1-py3.10-win-amd64.egg/EGG-INFO/requires.txt
eggs/BTrees-6.1-py3.10-win-amd64.egg/EGG-INFO/top_level.txt
eggs/ZConfig-4.2-py3.10.egg/EGG-INFO/LICENSE.txt
eggs/ZConfig-4.2-py3.10.egg/EGG-INFO/entry_points.txt
eggs/ZConfig-4.2-py3.10.egg/EGG-INFO/requires.txt
eggs/ZConfig-4.2-py3.10.egg/EGG-INFO/top_level.txt
eggs/ZConfig-4.2-py3.10.egg/ZConfig/schemaless.txt
eggs/ZConfig-4.2-py3.10.egg/ZConfig/tests/input/non-ascii.txt
eggs/ZConfig-4.2-py3.10.egg/ZConfig/tests/library/README.txt
eggs/ZConfig-4.2-py3.10.egg/ZConfig/tests/zipsource/README.txt
eggs/cffi-2.0.0-py3.10-win-amd64.egg/EGG-INFO/entry_points.txt
eggs/cffi-2.0.0-py3.10-win-amd64.egg/EGG-INFO/requires.txt
eggs/cffi-2.0.0-py3.10-win-amd64.egg/EGG-INFO/top_level.txt
eggs/coverage-7.10.7-py3.10-win-amd64.egg/EGG-INFO/entry_points.txt
eggs/coverage-7.10.7-py3.10-win-amd64.egg/EGG-INFO/requires.txt
eggs/coverage-7.10.7-py3.10-win-amd64.egg/EGG-INFO/top_level.txt
eggs/coverage-7.10.7-py3.10-win-amd64.egg/EGG-INFO/licenses/LICENSE.txt
eggs/dnspython-2.8.0-py3.10.egg/EGG-INFO/requires.txt
eggs/future-1.0.0-py3.10.egg/EGG-INFO/LICENSE.txt
eggs/future-1.0.0-py3.10.egg/EGG-INFO/entry_points.txt
eggs/future-1.0.0-py3.10.egg/EGG-INFO/top_level.txt
eggs/m01.fake-3.13.3-py3.10.egg/EGG-INFO/SOURCES.txt
eggs/m01.fake-3.13.3-py3.10.egg/EGG-INFO/dependency_links.txt
eggs/m01.fake-3.13.3-py3.10.egg/EGG-INFO/namespace_packages.txt
eggs/m01.fake-3.13.3-py3.10.egg/EGG-INFO/requires.txt
eggs/m01.fake-3.13.3-py3.10.egg/EGG-INFO/top_level.txt
eggs/m01.fake-3.13.3-py3.10.egg/m01/fake/README.txt
eggs/m01.fake-3.13.3-py3.10.egg/m01/fake/client.txt
eggs/m01.fake-3.13.3-py3.10.egg/m01/fake/collection-find.txt
eggs/m01.fake-3.13.3-py3.10.egg/m01/fake/collection-update.txt
eggs/m01.fake-3.13.3-py3.10.egg/m01/fake/collection.txt
eggs/m01.fake-3.13.3-py3.10.egg/m01/fake/database.txt
eggs/m01.fake-3.13.3-py3.10.egg/m01/fake/finder.txt
eggs/m01.fake-3.13.3-py3.10.egg/m01/fake/index.txt
eggs/m01.fake-3.13.3-py3.10.egg/m01/fake/testing.txt
eggs/m01.fake-3.13.3-py3.10.egg/m01/fake/sandbox/LICENSE-Community.txt
eggs/m01.mongo-3.13.5-py3.10.egg/EGG-INFO/SOURCES.txt
eggs/m01.mongo-3.13.5-py3.10.egg/EGG-INFO/dependency_links.txt
eggs/m01.mongo-3.13.5-py3.10.egg/EGG-INFO/namespace_packages.txt
eggs/m01.mongo-3.13.5-py3.10.egg/EGG-INFO/requires.txt
eggs/m01.mongo-3.13.5-py3.10.egg/EGG-INFO/top_level.txt
eggs/m01.mongo-3.13.5-py3.10.egg/m01/mongo/README.txt
eggs/m01.mongo-3.13.5-py3.10.egg/m01/mongo/index.txt
eggs/m01.mongo-3.13.5-py3.10.egg/m01/mongo/testing/sandbox/LICENSE-Community.txt
eggs/m01.mongo-3.13.5-py3.10.egg/m01/mongo/tests/advanced.txt
eggs/m01.mongo-3.13.5-py3.10.egg/m01/mongo/tests/batching.txt
eggs/m01.mongo-3.13.5-py3.10.egg/m01/mongo/tests/client.txt
eggs/m01.mongo-3.13.5-py3.10.egg/m01/mongo/tests/container.txt
eggs/m01.mongo-3.13.5-py3.10.egg/m01/mongo/tests/geo.txt
eggs/m01.mongo-3.13.5-py3.10.egg/m01/mongo/tests/geopoint.txt
eggs/m01.mongo-3.13.5-py3.10.egg/m01/mongo/tests/object.txt
eggs/m01.mongo-3.13.5-py3.10.egg/m01/mongo/tests/shared.txt
eggs/m01.mongo-3.13.5-py3.10.egg/m01/mongo/tests/storage.txt
eggs/m01.mongo-3.13.5-py3.10.egg/m01/mongo/tests/testing.txt
eggs/m01.mongo-3.13.5-py3.10.egg/m01/mongo/tests/transaction.txt
eggs/m01.mongo-3.13.5-py3.10.egg/m01/mongo/tests/usecase.txt
eggs/m01.mongo-3.13.5-py3.10.egg/m01/mongo/tests/util.txt
eggs/m01.mongo-3.13.5-py3.10.egg/m01/mongo/tests/zope.schema.txt
eggs/m01.stub-3.13.1-py3.10.egg/EGG-INFO/SOURCES.txt
eggs/m01.stub-3.13.1-py3.10.egg/EGG-INFO/dependency_links.txt
eggs/m01.stub-3.13.1-py3.10.egg/EGG-INFO/namespace_packages.txt
eggs/m01.stub-3.13.1-py3.10.egg/EGG-INFO/requires.txt
eggs/m01.stub-3.13.1-py3.10.egg/EGG-INFO/top_level.txt
eggs/m01.stub-3.13.1-py3.10.egg/m01/stub/README.txt
eggs/multipart-1.3.0-py3.10.egg/EGG-INFO/requires.txt
eggs/p01.env-0.5.2-py3.10.egg/EGG-INFO/SOURCES.txt
eggs/p01.env-0.5.2-py3.10.egg/EGG-INFO/dependency_links.txt
eggs/p01.env-0.5.2-py3.10.egg/EGG-INFO/namespace_packages.txt
eggs/p01.env-0.5.2-py3.10.egg/EGG-INFO/requires.txt
eggs/p01.env-0.5.2-py3.10.egg/EGG-INFO/top_level.txt
eggs/p01.recipe.setup-0.8.19-py3.10.egg/EGG-INFO/SOURCES.txt
eggs/p01.recipe.setup-0.8.19-py3.10.egg/EGG-INFO/dependency_links.txt
eggs/p01.recipe.setup-0.8.19-py3.10.egg/EGG-INFO/entry_points.txt
eggs/p01.recipe.setup-0.8.19-py3.10.egg/EGG-INFO/namespace_packages.txt
eggs/p01.recipe.setup-0.8.19-py3.10.egg/EGG-INFO/requires.txt
eggs/p01.recipe.setup-0.8.19-py3.10.egg/EGG-INFO/top_level.txt
eggs/persistent-6.3-py3.10-win-amd64.egg/EGG-INFO/requires.txt
eggs/persistent-6.3-py3.10-win-amd64.egg/EGG-INFO/top_level.txt
eggs/persistent-6.3-py3.10-win-amd64.egg/EGG-INFO/licenses/LICENSE.txt
eggs/pycparser-2.23-py3.10.egg/EGG-INFO/top_level.txt
eggs/pymongo-4.15.3-py3.10-win-amd64.egg/EGG-INFO/requires.txt
eggs/python_gettext-5.0-py3.10.egg/EGG-INFO/top_level.txt
eggs/pytz-2025.2-py3.10.egg/EGG-INFO/LICENSE.txt
eggs/pytz-2025.2-py3.10.egg/EGG-INFO/top_level.txt
eggs/sentinels-1.1.1-py3.10.egg/EGG-INFO/requires.txt
eggs/six-1.17.0-py3.10.egg/EGG-INFO/top_level.txt
eggs/transaction-5.0-py3.10.egg/EGG-INFO/LICENSE.txt
eggs/transaction-5.0-py3.10.egg/EGG-INFO/requires.txt
eggs/transaction-5.0-py3.10.egg/EGG-INFO/top_level.txt
eggs/z3c.coverage-2.1.0-py3.10.egg/EGG-INFO/SOURCES.txt
eggs/z3c.coverage-2.1.0-py3.10.egg/EGG-INFO/dependency_links.txt
eggs/z3c.coverage-2.1.0-py3.10.egg/EGG-INFO/entry_points.txt
eggs/z3c.coverage-2.1.0-py3.10.egg/EGG-INFO/namespace_packages.txt
eggs/z3c.coverage-2.1.0-py3.10.egg/EGG-INFO/requires.txt
eggs/z3c.coverage-2.1.0-py3.10.egg/EGG-INFO/top_level.txt
eggs/zc.recipe.egg-2.0.7-py3.10.egg/EGG-INFO/SOURCES.txt
eggs/zc.recipe.egg-2.0.7-py3.10.egg/EGG-INFO/dependency_links.txt
eggs/zc.recipe.egg-2.0.7-py3.10.egg/EGG-INFO/entry_points.txt
eggs/zc.recipe.egg-2.0.7-py3.10.egg/EGG-INFO/namespace_packages.txt
